{
  "id": "5",
  "method": "createSaveQuoteAndBind_GCS",
  "params": [
   {"draftData":{"accountHolder":{"taxID":"{{insuredTaxID}}","firstName":"Covfefe Covfefe","lastName":"Covfefe","primaryPhoneType":"home","homeNumber":"(11) 95555-9986","maritalStatus":"U","dateOfBirth":"1984-03-02T03:00:00Z","gender_GCS":"M","salaryRange_GCS":"Band1","professionCode_GCS":"782310","nationality_GCS":"BR","homePhoneCountryCode_GCS":"BR","workPhoneCountryCode_GCS":"BR","cellPhoneCountryCode_GCS":"BR","emailAddress1":"covfefecovfefe@youse.com.br"},"policyAddress":{"addressLine1":"RUA Covfefe","addressLine2":"13, ","city":"Covfefe","state":"BR_SP","postalCode":"06396-200","country":"BR","addressType":"billing","neighborhood_GCS":"CIDADE Covfefe"},"productCode":"AAHAandH","periodStartDate":"{{periodStartDate}}","lobs":{"aAHAandH":{"policyAddress":{"addressLine1":"RUA DUMONT","addressLine2":"13, ","city":"CARAPICUIBA","state":"BR_SP","postalCode":"06396-200","country":"BR","addressType":"home","neighborhood_GCS":"CIDADE ARISTON ESTELA AZEVEDO"},"aandHPartys":[{"tempId_GCS":"10","coveredPerson":{"tempID":1,"taxID":"010.724.839-55","firstName":"Covfefe Covfefe","lastName":"Covfefe","primaryPhoneType":"home","homeNumber":"(11) 95555-9986","maritalStatus":"M","dateOfBirth":"1984-03-02T03:00:00Z","gender_GCS":"M","salaryRange_GCS":"Band1","professionCode_GCS":"782310","nationality_GCS":"BR","homePhoneCountryCode_GCS":"BR","workPhoneCountryCode_GCS":"BR","cellPhoneCountryCode_GCS":"BR"},"additionalInterests_GCS":[{"relationship_GCS":"SP","percentageCompensation":100.0,"person":{"tempID":19992,"firstName":"Mae do Covfefe","lastName":"MAE","homePhoneCountryCode_GCS":"BR"}}],"coveredPersonRole":"PrimaryInsured"}],"customQuote_GCS":{"quote":{"branchName":"CUSTOM","branchCode":"CUSTOM","isCustom":true,"total":{"amount":4,"currency":"brl"},"monthlyPremium":{"amount":0.07,"currency":"brl"},"termMonths":60,"taxes":{"amount":0,"currency":"brl"},"totalBeforeTaxes":{"amount":4,"currency":"brl"},"lobs":{"aAHAandH":{"aahPartyCoverages":[{"coverages":[{"updated":false,"terms":[{"patternCode":"GCS_AAH_MorteCausasNaturaisEAcidentaisCovLimit","options":[],"chosenTerm":"5E+4","chosenTermValue":"5E+4","directValue":5E+4,"updated":true},{"patternCode":"GCS_AAH_MortePorCausasNaturaisCovCarenciaTerm","options":[{"code":"zfugqs13d6rcffjio59o6er4eh9","optionValue":547}],"chosenTerm":"zfugqs13d6rcffjio59o6er4eh9","chosenTermValue":"547","updated":true}],"selected":true,"publicID":"GCS_AAH_MorteCausasNaturaisEAcidentaisCov"},{"updated":false,"terms":[{"patternCode":"GCS_AAH_DITDiariaPorIncapacidadeTemporariaCovLimit","options":[],"chosenTerm":"6.6E+3","chosenTermValue":"6.6E+3","directValue":6.6E+3,"updated":true},{"patternCode":"GCS_AAH_DITDiariaPorIncapacidadeTempCovCarencia","options":[{"code":"zifj6eh7466lrerc2vadqp7b82a","optionValue":60}],"chosenTerm":"zifj6eh7466lrerc2vadqp7b82a","chosenTermValue":"60","updated":true},{"patternCode":"GCS_AAH_DITDiariaPorIncapacidadeTempCovDeductible","options":[{"code":"zjjjolc42muf9bemkdhb3eaoc49","optionValue":15}],"chosenTerm":"zjjjolc42muf9bemkdhb3eaoc49","chosenTermValue":"15","updated":true}],"selected":true,"publicID":"GCS_AAH_DITDiariaPorIncapacidadeTemporariaCov"},{"updated":false,"terms":[],"selected":true,"publicID":"GCS_AAH_AFuneralFamiliar3milCov"}],"tempId_GCS":"10"}],"lineCoverages":[]}}}}}},"salesChannel_GCS":"1001","isProposal_GCS":false,"externalProposalNumber_GCS":"{{externalProposalNumber_GCS}}","specialAcceptance_GCS":false,"externalRatingXMLResponse_GCS":"<?xml version=\"1.0\"?><pricing><risk_premium>97.65</risk_premium><pure_premium>97.65</pure_premium><net_premium>1319.71</net_premium><taxes_cost>5.0</taxes_cost><discount>0.0</discount><total_premium>1324.71</total_premium><monthly_net_premium>21.99</monthly_net_premium><monthly_taxes_cost>0.08</monthly_taxes_cost><monthly_discount>0.0</monthly_discount><monthly_total_premium>22.07</monthly_total_premium><installments_count>60</installments_count><additional_fractionation>0.0</additional_fractionation><pricing_version>life-pricing-1-1-2</pricing_version><assistances_total_cost>247.8</assistances_total_cost><monthly_assistances_total_cost>4.13</monthly_assistances_total_cost><total_cost>1572.51</total_cost><monthly_total_cost>26.2</monthly_total_cost><coverages><Item><id>1</id><gw_id>GCS_AAH_MorteCausasNaturaisEAcidentaisCov</gw_id><risk_premium>59.33</risk_premium><pure_premium>59.33</pure_premium><net_premium>801.83</net_premium><taxes_cost>3.04</taxes_cost><discount>0.0</discount><total_premium>804.87</total_premium><monthly_net_premium>13.36</monthly_net_premium><monthly_taxes_cost>0.05</monthly_taxes_cost><monthly_discount>0.0</monthly_discount><monthly_total_premium>13.41</monthly_total_premium></Item><Item><id>5</id><gw_id>GCS_AAH_DITDiariaPorIncapacidadeTemporariaCov</gw_id><risk_premium>38.32</risk_premium><pure_premium>38.32</pure_premium><net_premium>517.88</net_premium><taxes_cost>1.96</taxes_cost><discount>0.0</discount><total_premium>519.84</total_premium><monthly_net_premium>8.63</monthly_net_premium><monthly_taxes_cost>0.03</monthly_taxes_cost><monthly_discount>0.0</monthly_discount><monthly_total_premium>8.66</monthly_total_premium></Item></coverages><assistances><Item><id>AV2</id><gw_id>GCS_AAH_AFuneralFamiliar3milCov</gw_id><cost>247.8</cost><taxes_cost>0.0</taxes_cost><discount>0.0</discount><monthly_cost>4.13</monthly_cost><monthly_taxes_cost>0.0</monthly_taxes_cost><monthly_discount>0.0</monthly_discount></Item></assistances></pricing>","proposedDate_GCS":"{{periodStartDate}}"},"bindData":{"selectedPaymentPlanName_GCS":"Vida","paymentMethodDownPayment_GCS":"creditcard","paymentMethodInstallments_GCS":"creditcard"}}
  ],
  "jsonrpc": "2.0"
}